odoo/addons/hr_holidays_credit/README.rst
odoo/addons/hr_holidays_credit/__init__.py
odoo/addons/hr_holidays_credit/__manifest__.py
odoo/addons/hr_holidays_credit/i18n/ca.po
odoo/addons/hr_holidays_credit/i18n/fr.po
odoo/addons/hr_holidays_credit/i18n/hr_holidays_credit.pot
odoo/addons/hr_holidays_credit/i18n/it.po
odoo/addons/hr_holidays_credit/models/__init__.py
odoo/addons/hr_holidays_credit/models/hr_leave.py
odoo/addons/hr_holidays_credit/models/hr_leave_type.py
odoo/addons/hr_holidays_credit/readme/CONTRIBUTORS.rst
odoo/addons/hr_holidays_credit/readme/DESCRIPTION.rst
odoo/addons/hr_holidays_credit/static/description/icon.png
odoo/addons/hr_holidays_credit/static/description/index.html
odoo/addons/hr_holidays_credit/tests/__init__.py
odoo/addons/hr_holidays_credit/tests/test_hr_holidays_credit.py
odoo/addons/hr_holidays_credit/views/hr_leave_type.xml
odoo13_addon_hr_holidays_credit-13.0.1.1.0.dist-info/METADATA
odoo13_addon_hr_holidays_credit-13.0.1.1.0.dist-info/WHEEL
odoo13_addon_hr_holidays_credit-13.0.1.1.0.dist-info/top_level.txt
odoo13_addon_hr_holidays_credit-13.0.1.1.0.dist-info/RECORD
